ali/__init__.py
ali/dataframe.py
ali/excel.py
ali/image.py
aminatu/__init__.py
aminatu/sql.py
ana/__init__.py
ana/http.py
conda/__init__.py
conda/hub.py
conda/main.py
kukukan/__init__.py
kukukan/image.py
kukukan/panda.py
kukukan/sound.py
memory/__init__.py
memory/database.py
memory/main.py
moril-2.2.6.dist-info/METADATA
moril-2.2.6.dist-info/WHEEL
moril-2.2.6.dist-info/top_level.txt
moril-2.2.6.dist-info/RECORD
