Metadata-Version: 2.1
Name: moril
Version: 2.2.6
Summary: manden packages
Author: Ana Keita
Author-email: keita.kukukhan@gmail.com
Requires-Python: >=3.9.6
Requires-Dist: pandas
Requires-Dist: sqlalchemy
Requires-Dist: Pillow
Requires-Dist: openpyxl
